lgh/__init__.py
lgh/lgh.py
lazy_ghost_hunters-2.1.3.dist-info/entry_points.txt
lazy_ghost_hunters-2.1.3.dist-info/WHEEL
lazy_ghost_hunters-2.1.3.dist-info/METADATA
lazy_ghost_hunters-2.1.3.dist-info/RECORD
