Metadata-Version: 2.1
Name: lazy-ghost-hunters
Version: 2.1.3
Summary: Lazy Ghost Hunters is a solver for the game Ghost Hunters from Smart Games
Home-page: https://github.com/matteli/lazy-ghost-hunters
License: MIT
Author: matteli
Author-email: matthieu.nue@gmail.com
Requires-Python: >=3.6,<4.0
Classifier: License :: OSI Approved :: MIT License
Classifier: Programming Language :: Python :: 3
Classifier: Programming Language :: Python :: 3.10
Classifier: Programming Language :: Python :: 3.6
Classifier: Programming Language :: Python :: 3.7
Classifier: Programming Language :: Python :: 3.8
Classifier: Programming Language :: Python :: 3.9
Project-URL: Repository, https://github.com/matteli/lazy-ghost-hunters
